psopt/__init__.py
psopt/combination/__init__.py
psopt/combination/optimizer.py
psopt/commons/__init__.py
psopt/commons/optimizer.py
psopt/continuous/__init__.py
psopt/continuous/optimizer.py
psopt/permutation/__init__.py
psopt/permutation/optimizer.py
psopt/utils/__init__.py
psopt/utils/evaluate_constraints.py
psopt/utils/logger.py
psopt/utils/metrics.py
psopt/utils/results.py
psopt/utils/seeder.py
psopt-0.1.2.dist-info/LICENSE
psopt-0.1.2.dist-info/METADATA
psopt-0.1.2.dist-info/WHEEL
psopt-0.1.2.dist-info/top_level.txt
psopt-0.1.2.dist-info/RECORD
