Metadata-Version: 2.1
Name: psopt
Version: 0.1.2
Summary: A particle swarm optimizer for general use
Home-page: https://github.com/artur-deluca/psopt
Author: Artur de Luca
Author-email: arturbackdeluca@gmail.com
License: UNKNOWN
Platform: UNKNOWN
Classifier: Development Status :: 3 - Alpha
Classifier: License :: OSI Approved :: MIT License
Classifier: Programming Language :: Python :: 3
Classifier: Topic :: Scientific/Engineering
Requires-Dist: dill
Requires-Dist: multiprocess
Requires-Dist: numpy
Requires-Dist: matplotlib
Provides-Extra: all
Requires-Dist: dill ; extra == 'all'
Requires-Dist: multiprocess ; extra == 'all'
Requires-Dist: numpy ; extra == 'all'
Requires-Dist: matplotlib ; extra == 'all'
Requires-Dist: pytest ; extra == 'all'
Requires-Dist: pytest-cov ; extra == 'all'
Requires-Dist: flake8 ; extra == 'all'
Requires-Dist: codecov ; extra == 'all'
Requires-Dist: sphinx ; extra == 'all'
Requires-Dist: sphinx-gallery ; extra == 'all'
Provides-Extra: dev
Requires-Dist: dill ; extra == 'dev'
Requires-Dist: multiprocess ; extra == 'dev'
Requires-Dist: numpy ; extra == 'dev'
Requires-Dist: matplotlib ; extra == 'dev'
Requires-Dist: pytest ; extra == 'dev'
Requires-Dist: pytest-cov ; extra == 'dev'
Requires-Dist: flake8 ; extra == 'dev'
Requires-Dist: codecov ; extra == 'dev'
Provides-Extra: doc
Requires-Dist: dill ; extra == 'doc'
Requires-Dist: multiprocess ; extra == 'doc'
Requires-Dist: numpy ; extra == 'doc'
Requires-Dist: matplotlib ; extra == 'doc'
Requires-Dist: sphinx ; extra == 'doc'
Requires-Dist: sphinx-gallery ; extra == 'doc'
